<?xml version="1.0"?>

<contentStruct>
    <element id="1">
        <name>Article</name>
        <description>lorem ipsum</description>
        <types>
            <type refType="1">
                <name>Titre</name>
                <limit>60</limit>
            </type>
            <type refType="4">
                <name>Image</name>
            </type>
            <type refType="2">
                <name>Chapeau</name>
                <limit>450</limit>
            </type>
            <type refType="2">
                <name>Contenu</name>
                <limit>0</limit>
            </type>
        </types>
    </element>
</contentStruct>